{"info":{"_postman_id":"82895252-be63-46be-ab56-ae42ef0a0b93","name":"repoVersion-3 doc 1","schema":"https://schema.getpostman.com/json/collection/v2.1.0/collection.json"},"item":[{"name":"Sample endpoint: Returns details about a particular user","id":"ac5bf699-122b-4bb3-9bf8-4c47d4c938fb","request":{"method":"GET","header":[],"url":{"raw":"{{baseUrl}}/user?id=-97613701","host":["{{baseUrl}}"],"path":["user"],"query":[{"key":"id","value":"-97613701","description":"(Required) ID of the user"}]}},"response":[{"id":"423cc03a-7ed6-4f6c-9cac-4e29d57a3d4a","name":"Sample response: Details about a user by ID","originalRequest":{"method":"GET","header":[],"url":{"raw":"{{baseUrl}}/user?id=-97613701","host":["{{baseUrl}}"],"path":["user"],"query":[{"key":"id","value":"-97613701"}]}},"status":"OK","code":200,"_postman_previewlanguage":"json","header":[{"disabled":false,"description":"A link to the next page of responses","key":"x-next","value":"consectetur ullamco ex minim Ut"},{"key":"Content-Type","value":"application/json"}],"cookie":[],"responseTime":null,"body":"{\n \"id\": 39348183,\n \"name\": \"occaecat laboris\",\n \"tag\": \"non sunt in\"\n}"},{"id":"3da98cdb-bc32-401b-97fc-f41b1b3e078b","name":"Unexpected error","originalRequest":{"method":"GET","header":[],"url":{"raw":"{{baseUrl}}/user?id=-97613701","host":["{{baseUrl}}"],"path":["user"],"query":[{"key":"id","value":"-97613701"}]}},"status":"Internal Server Error","code":500,"_postman_previewlanguage":"json","header":[{"key":"Content-Type","value":"application/json"}],"cookie":[],"responseTime":null,"body":"{\n \"code\": -71322621,\n \"message\": \"ex\"\n}"}]}],"variable":[{"id":"33dd0599-1f94-4096-bdf1-5ab97fc838f2","key":"baseUrl","value":"http://localhost:3000s","type":"string"}]}